crispy_views/__init__.py
crispy_views/forms.py
crispy_views/mixins.py
crispy_views/tables.py
crispy_views/views.py
django_crispy_views-1.0.1.dist-info/LICENSE
django_crispy_views-1.0.1.dist-info/METADATA
django_crispy_views-1.0.1.dist-info/WHEEL
django_crispy_views-1.0.1.dist-info/top_level.txt
django_crispy_views-1.0.1.dist-info/RECORD
