Metadata-Version: 2.1
Name: django-crispy-views
Version: 1.0.1
Summary: crispy views for django.
Home-page: https://github.com/monim67/django-crispy-views
Author: Munim Munna
Author-email: monim67@yahoo.com
License: MIT
Keywords: crispy,views
Platform: UNKNOWN
Classifier: Intended Audience :: Developers
Classifier: Environment :: Web Environment
Classifier: Operating System :: OS Independent
Classifier: Programming Language :: Python
Classifier: Programming Language :: Python :: 3
Classifier: Framework :: Django
Classifier: Framework :: Django :: 2.0
Classifier: Framework :: Django :: 3.0
Classifier: Development Status :: 5 - Production/Stable
Classifier: License :: OSI Approved :: MIT License
Classifier: Topic :: Software Development :: Libraries
Classifier: Topic :: Software Development :: Version Control :: Git
Classifier: Topic :: Utilities
Requires-Python: >=3
Requires-Dist: django (>=2.0)
Requires-Dist: django-crispy-forms (>=1.8.1)
Requires-Dist: django-filter (>=2.2.0)
Requires-Dist: django-tables2 (>=2.2.1)
